mongobase/__init__.py
mongobase/config.py
mongobase/exceptions.py
mongobase/modelbase.py
mongobase/mongobase.py
mongobase-0.3.1a0.dist-info/LICENSE
mongobase-0.3.1a0.dist-info/METADATA
mongobase-0.3.1a0.dist-info/WHEEL
mongobase-0.3.1a0.dist-info/top_level.txt
mongobase-0.3.1a0.dist-info/RECORD
