Metadata-Version: 2.1
Name: mongobase
Version: 0.3.1a0
Summary: A lightweight Pythonic OR Mapper for MongoDB.
Home-page: https://github.com/kazukiotsuka/mongobase
Author: Kazuki Otsuka
Author-email: otsuka.kazuki@googlemail.com
License: MIT
Keywords: mongodb,mongo,pymongo,orm,or mapper
Platform: UNKNOWN
Classifier: License :: OSI Approved :: MIT License
Classifier: Programming Language :: Python :: 3.7
Classifier: Intended Audience :: Developers
Classifier: Topic :: Database :: Front-Ends
Classifier: Topic :: Software Development :: Libraries
Requires-Python: ~=3.6
Requires-Dist: pymongo (>=3.6.0)
